loafer/__init__.py
loafer/_compat.py
loafer/dispatchers.py
loafer/exceptions.py
loafer/managers.py
loafer/message_translators.py
loafer/providers.py
loafer/py.typed
loafer/routes.py
loafer/runners.py
loafer/types.py
loafer/ext/__init__.py
loafer/ext/sentry.py
loafer/ext/aws/__init__.py
loafer/ext/aws/bases.py
loafer/ext/aws/handlers.py
loafer/ext/aws/message_translators.py
loafer/ext/aws/providers.py
loafer/ext/aws/routes.py
olist_loafer-7.0.0.dist-info/METADATA
olist_loafer-7.0.0.dist-info/WHEEL
olist_loafer-7.0.0.dist-info/licenses/LICENSE
olist_loafer-7.0.0.dist-info/RECORD
