Metadata-Version: 2.4
Name: olist-loafer
Version: 7.0.0
Summary: Asynchronous message dispatcher for concurrent tasks processing
Project-URL: Download, https://github.com/olist/olist-loafer/releases
Project-URL: Repository, https://github.com/olist/olist-loafer/
Author-email: Olist <developers@olist.com>
License: The MIT License (MIT)
License-File: LICENSE
Keywords: asyncio,dispatcher,message,microservices,tasks
Classifier: Development Status :: 4 - Beta
Classifier: Environment :: Console
Classifier: Intended Audience :: Developers
Classifier: License :: OSI Approved :: MIT License
Classifier: Natural Language :: English
Classifier: Operating System :: OS Independent
Classifier: Programming Language :: Python :: 3 :: Only
Classifier: Programming Language :: Python :: 3.11
Classifier: Programming Language :: Python :: 3.12
Classifier: Programming Language :: Python :: 3.13
Classifier: Topic :: System :: Distributed Computing
Requires-Python: >=3.11
Requires-Dist: aiobotocore<3.0.0,>=2.0.0
Requires-Dist: types-aiobotocore[sns,sqs]<3.0.0,>=2.0.0
Requires-Dist: typing-extensions; python_version < '3.12'
Provides-Extra: sentry
Requires-Dist: sentry-sdk>=2.0; extra == 'sentry'
